Metadata-Version: 1.0
Name: FTP-MU
Version: 0.0
Summary: Gaussian and Binomial distributions
Home-page: UNKNOWN
Author: UNKNOWN
Author-email: isofgh@gmail.com
License: UNKNOWN
Platform: UNKNOWN
